pykeepass_cache/__init__.py
pykeepass_cache/pykeepass_cache.py
pykeepass_cache-2.0.3.dist-info/LICENSE
pykeepass_cache-2.0.3.dist-info/METADATA
pykeepass_cache-2.0.3.dist-info/WHEEL
pykeepass_cache-2.0.3.dist-info/top_level.txt
pykeepass_cache-2.0.3.dist-info/RECORD
