Metadata-Version: 2.1
Name: pykeepass-cache
Version: 2.0.3
Summary: database caching for PyKeePass
Home-page: https://github.com/evidlo/pykeepass_cache
Author: Evan Widloski
Author-email: evan@evanw.org
License: GPL3
Platform: UNKNOWN
Requires-Dist: pykeepass
Requires-Dist: python-daemon
Requires-Dist: rpyc
